autoastro/__init__.py
autoastro/dimensions.py
autoastro/exc.py
autoastro/lensing.py
autoastro/galaxy/__init__.py
autoastro/galaxy/fit_galaxy.py
autoastro/galaxy/galaxy.py
autoastro/galaxy/galaxy_data.py
autoastro/galaxy/galaxy_model.py
autoastro/galaxy/masked_galaxy_data.py
autoastro/hyper/__init__.py
autoastro/hyper/hyper_data.py
autoastro/plot/__init__.py
autoastro/plot/fit_galaxy_plots.py
autoastro/plot/galaxy_plots.py
autoastro/plot/lensing_mat_objs.py
autoastro/plot/lensing_plotters.py
autoastro/plot/light_profile_plots.py
autoastro/plot/mass_profile_plots.py
autoastro/profiles/__init__.py
autoastro/profiles/geometry_profiles.py
autoastro/profiles/light_and_mass_profiles.py
autoastro/profiles/light_profiles.py
autoastro/profiles/mass_profiles/__init__.py
autoastro/profiles/mass_profiles/dark_mass_profiles.py
autoastro/profiles/mass_profiles/mass_profiles.py
autoastro/profiles/mass_profiles/mass_sheets.py
autoastro/profiles/mass_profiles/stellar_mass_profiles.py
autoastro/profiles/mass_profiles/total_mass_profiles.py
autoastro/util/__init__.py
autoastro/util/cosmology_util.py
test_autoastro/__init__.py
test_autoastro/conftest.py
test_autoastro/mock/__init__.py
test_autoastro/mock/mock_cosmology.py
test_autoastro/mock/mock_galaxy.py
test_autoastro/mock/mock_profiles.py
test_autoastro/profiling/__init__.py
test_autoastro/profiling/light_profiles/__init__.py
test_autoastro/profiling/light_profiles/intensities.py
test_autoastro/profiling/mass_profiles/__init__.py
test_autoastro/profiling/mass_profiles/deflections.py
test_autoastro/profiling/mass_profiles/deflections_gaussians.py
test_autoastro/profiling/mass_profiles/deflections_interpolation.py
test_autoastro/unit/__init__.py
test_autoastro/unit/conftest.py
test_autoastro/unit/test_dimensions.py
test_autoastro/unit/test_lensing.py
test_autoastro/unit/galaxy/__init__.py
test_autoastro/unit/galaxy/test_fit_galaxy.py
test_autoastro/unit/galaxy/test_galaxy.py
test_autoastro/unit/galaxy/test_galaxy_data.py
autoastro-0.7.2.dist-info/LICENSE
autoastro-0.7.2.dist-info/METADATA
autoastro-0.7.2.dist-info/WHEEL
autoastro-0.7.2.dist-info/top_level.txt
autoastro-0.7.2.dist-info/RECORD
