Metadata-Version: 2.1
Name: autoastro
Version: 0.7.2
Summary: Astro modelling
Home-page: https://github.com/jammy2211/PyAutoAstro
Author: James Nightingale and Richard Hayes
Author-email: james.w.nightingale@durham.ac.uk
License: MIT License
Keywords: cli
Platform: UNKNOWN
Classifier: Intended Audience :: Science/Research
Classifier: Topic :: Scientific/Engineering :: Physics
Classifier: License :: OSI Approved :: MIT License
Classifier: Natural Language :: English
Classifier: Operating System :: OS Independent
Classifier: Programming Language :: Python :: 3
Classifier: Programming Language :: Python :: 3.2
Classifier: Programming Language :: Python :: 3.3
Classifier: Programming Language :: Python :: 3.4
Classifier: Programming Language :: Python :: 3.5
Classifier: Programming Language :: Python :: 3.6
Classifier: Programming Language :: Python :: 3.7
Requires-Dist: astropy (>=3.0.0)
Requires-Dist: autoarray (==0.10.4)
Requires-Dist: autofit (==0.56.0)
Requires-Dist: colossus (==1.2.14)
Requires-Dist: numpy (>=1.18.0)
Requires-Dist: pyquad (==0.0.4.0)
Provides-Extra: test
Requires-Dist: coverage ; extra == 'test'
Requires-Dist: pytest ; extra == 'test'
Requires-Dist: pytest-cov ; extra == 'test'
